{
  "08708F6A-C3BA-4187-B5C9-061DE38C64E7": {
    "annotations": [
      [
        "ૐ નમ શિવાય"
      ],
      [
        "sutracharkha",
        "सुं्रचरखा"
      ],
      [
        "handmade",
        "textiles",
        "னி",
        "பாளி"
      ],
      [
        "ટ્રિટ"
      ],
      [
        "ਈਦਮ",
        "arama"
      ],
      [
        "shop",
        "ம்ய"
      ],
      [
        "ഠ",
        "win",
        "big"
      ]
    ]
  },
  "0A94950D-422F-49C6-A532-B7CFDF1943E4": {
    "annotations": [
      [
        "pav",
        "நொங்ஷைப்பியை",
        "since",
        "1971"
      ],
      [
        "पेवर्स",
        "इग्लैं"
      ],
      [
        "पेवर्स",
        "इंग्लैं"
      ],
      [
        "ഠ"
      ],
      [
        "25"
      ]
    ]
  },
  "0DD3F2CB-C26A-443E-B405-B3FE157AAE9D": {
    "annotations": [
      [
        "৪০০",
        "swarovsk"
      ],
      [
        "ଆଗ",
        "स्वारोवस्की",
        "୪୪୯"
      ],
      [
        "୪",
        "ପ୍ରତି"
      ],
      [
        "মহা",
        "౭౩"
      ],
      [
        "ഈ ",
        "దరీ"
      ],
      [
        "0000"
      ],
      [
        "swarovski",
        "swarovski",
        "swarovski"
      ]
    ]
  },
  "0FE64D39-090E-4ECD-9517-70E126DBB67F": {
    "annotations": [
      [
        "damilanoguarty",
        "italia"
      ],
      [
        "૯૦૦૦"
      ],
      [
        "രേഖ"
      ],
      [
        "ഠേ"
      ],
      [
        "0800"
      ],
      [
        "ഝേഝ"
      ],
      [
        "art"
      ],
      [
        "ಸೀಗಲಾರ"
      ],
      [
        "damilano"
      ],
      [
        "italia"
      ],
      [
        "fathers",
        "day"
      ],
      [
        "দে  ",
        " "
      ]
    ]
  },
  "178E646E-2983-4EE6-959A-BFE81EE1A343": {
    "annotations": [
      [
        "डिजीया.ा",
        "ईश्वार",
        "ૠ",
        "डिजीया.्ञा"
      ],
      [
        "ગંડાં માર",
        "ईश्वार"
      ],
      [
        "egates"
      ]
    ]
  },
  "22199945-0F58-426B-9961-D8AAB4BD1DC5": {
    "annotations": [
      [
        "make",
        "yourown",
        "perfume"
      ],
      [
        "वियुणरभानजंतम्"
      ],
      [
        "  ",
        "celebrating"
      ],
      [
        "20",
        "50",
        "૦૯૬૦૨૨૧૦૪૪૦૪૦",
        "50",
        "cellarativs"
      ],
      [
        "",
        "50"
      ],
      [
        "ఖ్ఙ",
        "stords",
        "૧૧"
      ],
      [
        "41",
        " ",
        "stores"
      ],
      [
        "ట్ఙ",
        "stores",
        "રન",
        "0000"
      ],
      [
        "40"
      ],
      [
        "ବିତଏସ",
        "૧"
      ],
      [
        "സമേളനം"
      ],
      [
        "50",
        "chaebrating"
      ],
      [
        "stures",
        "40",
        "50",
        "50"
      ],
      [
        "stores"
      ]
    ]
  },
  "26A62BF0-B01D-4D54-956B-14079FA81301": {
    "annotations": [
      [
        "પ્રતાપાફ્ટ",
        "മൈലേജിൽ",
        "ૠ",
        "ણ",
        "ગા",
        "ਸੀ",
        "୦୦୦ଏ"
      ],
      [
        "enchante",
        "its",
        "enchante"
      ],
      [
        "કાજદાજ",
        "180300037199"
      ],
      [
        "uchai",
        "ശ്രീ"
      ],
      [
        "੪੦੦",
        "8420",
        "hrrdingedenthtraphy",
        "chilled"
      ],
      [
        "its",
        "chai"
      ],
      [
        "ചളിപ്പറമ്പ്",
        "ક્શરના",
        "૧૩૪૦",
        "rua",
        "પ્રમ",
        "pego",
        "ਕਾਰਾ",
        "stringsstud",
        "1243",
        "an",
        "76"
      ],
      [
        "ધનવન",
        "maga"
      ],
      [
        "લ્ય"
      ],
      [
        "easonshot"
      ],
      [
        " "
      ]
    ]
  },
  "2927D871-AC25-4E8F-BED3-12ED547B489D": {
    "annotations": [
      [
        "philips"
      ],
      [
        "पिण्याचे",
        "पाणी"
      ],
      [
        "पीने",
        "का‍",
        "पानी"
      ],
      [
        "drinking",
        "water"
      ]
    ]
  },
  "370B5D27-05D3-4E34-95AA-6DE4D7133220": {
    "annotations": [
      [
        "बालाची",
        "देखभाल"
      ],
      [
        "शिशु",
        "देखभाल"
      ],
      [
        "baby",
        "care"
      ],
      [
        "प्राइपाणी"
      ],
      [
        "मकाली"
      ]
    ]
  },
  "3BFF08EA-CB49-411B-8EA6-C7CACC204CAC": {
    "annotations": [
      [
        "देशांतर्गत",
        "सुरक्षा",
        "तपासणी",
        "दिल्ली",
        "अंतर्देशीय"
      ],
      [
        "सुरक्षा",
        "जाँच"
      ],
      [
        "domestic",
        "security",
        "check",
        "m"
      ],
      [
        "आंतरराष्टीय",
        "सुरक्षा",
        "तपासणी",
        "ਕਾਰਾ",
        "अंतर्राष्ट्रय",
        "सुरक्षा",
        "जाँच"
      ],
      [
        "international",
        "security",
        "check",
        "m"
      ],
      [
        "അനാവിനെ"
      ]
    ]
  },
  "3F52C436-1E0E-48EA-A292-F884298E5E7E": {
    "annotations": [
      [
        "makaibar",
        "ଓ",
        "मवाईबारी",
        "তৃণমূল"
      ],
      [
        "୦୩ତମା",
        "359",
        "the",
        "tasting",
        "room"
      ],
      [
        "രോ"
      ]
    ]
  },
  "42B1016F-5F5D-4EDD-A2C3-2CE198B3F2BA": {
    "annotations": [
      [
        "कर्मचारी",
        "कर्मचारी"
      ],
      [
        "staff"
      ],
      [
        "ગામત"
      ]
    ]
  },
  "49884BBA-FF94-4CE0-A6A7-657BE0C901F8": {
    "annotations": [
      [
        "ਸਤਾ"
      ],
      [
        "আত্মী"
      ],
      [
        "সমিতি"
      ],
      [
        "सर्व",
        "आगमन",
        "ਦੀ",
        "सभी",
        "आगमन",
        "all",
        "arrival"
      ]
    ]
  },
  "5A3B6 NEW": {
    "annotations": [
      [
        "स्टारबक्स",
        "starbucks"
      ],
      [
        "31",
        "टाटा",
        "अलायंस"
      ],
      [
        "a",
        "tata",
        "alliance"
      ]
    ]
  },
  "6525130A-B007-4F98-81FD-0095612FDD8C": {
    "annotations": [
      [
        "૨",
        "૭",
        "ओपियम",
        "नया"
      ],
      [
        "sunglass",
        "lounge",
        "ਸਕਗਲਾਰ",
        "ਲਾਤਯ"
      ],
      [
        "big"
      ]
    ]
  },
  "6F153F5D-3F75-4166-A3DE-4F500AF19DF3": {
    "annotations": [
      [
        "तपासणी",
        "अंतर्देशीय",
        "सुरक्षा",
        "जाँच"
      ],
      [
        "देशांतर्गत",
        "सुरक्षा",
        "16",
        "m"
      ],
      [
        "domestic",
        "security",
        "check"
      ],
      [
        "आरक्षित",
        "आराम",
        "कक्ष",
        "ૠ",
        "आरक्षित",
        "आराम",
        "कक्ष"
      ],
      [
        "reserved",
        "lounge"
      ]
    ]
  },
  "7EE96909-CAA4-41E1-B286-E326E3D86234": {
    "annotations": [
      [
        "પિ"
      ],
      [
        "11519",
        "રા",
        "ડાં૧૮૯",
        "1978"
      ],
      [
        "भेल",
        "ॐ",
        "വോട്ടേവ്"
      ],
      [
        "चाट"
      ],
      [
        "કા151",
        "and",
        "chaat"
      ],
      [
        "મમદા"
      ],
      [
        "૩૦૦૦૦૦૨૪"
      ],
      [
        "iconcahi"
      ],
      [
        "૨૪૫૬૨",
        "૧૧૦૦૦૯2ર"
      ],
      [
        "24",
        "પ્રામ પંચાયરની"
      ],
      [
        " "
      ],
      [
        "0011241140"
      ]
    ]
  },
  "94C18ED9-3A33-4E98-961C-0F3128357C0C": {
    "annotations": [
      [
        "૬૪૪"
      ],
      [
        "010440",
        "૦",
        "દા"
      ],
      [
        "",
        "૯૫૧૦"
      ],
      [
        "1111010101010101010101000"
      ],
      [
        "પ્રણાલાલભદાયરામ"
      ],
      [
        "પ્રાયણ"
      ],
      [
        "भारतीय",
        "विमानपत्तन",
        "प्राधिकरण"
      ],
      [
        "airports",
        "authority",
        "of",
        "india"
      ],
      [
        "automonically"
      ],
      [
        "wwwkrajiceknet"
      ]
    ]
  },
  "A76BF814-1823-4B17-BA5B-55F2783F11AB": {
    "annotations": [
      [
        "9657231517",
        "820805055"
      ],
      [
        "durwa"
      ],
      [
        "dairy",
        "farm"
      ],
      [
        "इा डिजरीकारीम"
      ]
    ]
  },
  "A92D03CF-3F3D-4083-A06D-ABB190A8CEEA": {
    "annotations": [
      [
        "ദ്വാപിലം",
        "स्माइलेन"
      ],
      [
        "മുതൽ"
      ],
      [
        "remote",
        "control"
      ],
      [
        "remote",
        "control"
      ],
      [
        "construction"
      ],
      [
        "games",
        "puzzle"
      ],
      [
        "gamespuzzle",
        "లక్ష"
      ],
      [
        "પડા",
        "lego"
      ],
      [
        "creator",
        "euro"
      ],
      [
        "race",
        "૧૦"
      ],
      [
        "ਪਿ੫",
        "ਤਿ",
        "racenboll",
        "racenroll",
        "୪୦"
      ],
      [
        "stoln"
      ],
      [
        "big"
      ],
      [
        "ટ્રા૦૦"
      ]
    ]
  },
  "B68EE1E9-8A0B-483B-AE39-8D771BA84228": {
    "annotations": [
      [
        "ટ",
        "नोंदणी",
        "registration",
        "૬",
        "पंजीकरण"
      ],
      [
        "15"
      ]
    ]
  },
  "DBCE897F-DF91-4615-B58B-7B00B919C41A": {
    "annotations": [
      [
        " ",
        "रेने"
      ],
      [
        ""
      ],
      [
        "౭౦౦౦",
        "ഠേ",
        "૧૧૧૬"
      ],
      [
        "2000"
      ],
      [
        "0600"
      ],
      [
        "50"
      ],
      [
        "rence"
      ],
      [
        "buy2",
        "ગ્રાડ્રી"
      ],
      [
        "கோட"
      ],
      [
        "લખાયના"
      ]
    ]
  },
  "E43E2439-171F-4EAC-9D0E-40C1AA6FA064": {
    "annotations": [
      [
        "555",
        "आम",
        "আনন্তি",
        "उडान",
        "या‌त्री",
        "कँफे"
      ],
      [
        "उडान यात्रके"
      ],
      [
        "udan",
        "udan",
        "yatri",
        "cafe"
      ],
      [
        "उदास",
        "ਬੀ",
        "भारत्य"
      ],
      [
        "underscafe"
      ],
      [
        "শুন্দত",
        " "
      ]
    ]
  },
  "E848F404-15B3-477D-87B9-BDBCCCD96F7D": {
    "annotations": [
      [
        "ૠૠ"
      ],
      [
        "उद्दाहन",
        "ભય",
        "लिफ्ट",
        "২০০০"
      ],
      [
        "lift"
      ],
      [
        "पहिला",
        "मजला",
        "0",
        "प्रथम",
        "तल‍"
      ],
      [
        "firstfloor"
      ],
      [
        "तक्‍जला",
        "भू तल"
      ],
      [
        "ground",
        "floor"
      ]
    ]
  },
  "IMG_9699": {
    "annotations": [
      [
        "৩০",
        ""
      ]
    ]
  },
  "IMG_9700": {
    "annotations": [
      [
        "ગ્ડ"
      ],
      [
        "कॉम",
        "com"
      ]
    ]
  },
  "IMG_9701": {
    "annotations": [
      [
        "૬"
      ],
      [
        "7c1zh",
        "गो",
        "कलर्स"
      ]
    ]
  },
  "IMG_9703": {
    "annotations": [
      [
        "amohans",
        "ਸਿਰਾ"
      ],
      [
        "swee",
        "m",
        "r"
      ]
    ]
  },
  "IMG_9704": {
    "annotations": [
      [
        "स्टेलरहाट",
        "stellar",
        "haat",
        "tm"
      ],
      [
        "more",
        "of",
        "what",
        "you",
        "want"
      ],
      [
        "dream95",
        "enterprises",
        "gstn",
        "27",
        "abxp"
      ]
    ]
  },
  "IMG_9705": {
    "annotations": []
  },
  "IMG_9706": {
    "annotations": [
      [
        "झवामि",
        "ivame"
      ]
    ]
  },
  "IMG_9707": {
    "annotations": [
      [
        "૦"
      ]
    ]
  },
  "IMG_9720": {
    "annotations": [
      [
        "हाऊस",
        "dfh"
      ],
      [
        "ड्राय",
        "फ्रूट",
        " ",
        "મુશ"
      ],
      [
        "ન",
        "ઉમા",
        "૧૦૧૬૭"
      ],
      [
        "eat",
        "healthy"
      ]
    ]
  },
  "IMG_9721": {
    "annotations": [
      [
        "ਫ੍ਰ",
        "ब्युटी",
        "कलेक्शन"
      ],
      [
        "ਸਾਵਾਈ",
        "beauty"
      ],
      [
        "૦૧૦૦"
      ],
      [
        "makeup",
        "1",
        "skin",
        "care",
        "hair",
        "caro",
        "fashion",
        "accessories",
        "8",
        "saloon",
        "product"
      ]
    ]
  },
  "IMG_9722": {
    "annotations": [
      [
        "20115"
      ],
      [
        "ba",
        "વડા"
      ],
      [
        "पुणेबक्कहाऊर"
      ],
      [
        "bakery",
        "8",
        "cake",
        "shop"
      ]
    ]
  },
  "IMG_9723": {
    "annotations": [
      [
        "2",
        "૬"
      ],
      [
        "35",
        "૨"
      ],
      [
        "the",
        "ice",
        "cream",
        "sundae",
        "zone"
      ],
      [
        "पोलार",
        "વૅમર"
      ]
    ]
  },
  "IMG_9726": {
    "annotations": [
      [
        "k",
        "ality"
      ],
      [
        "alls",
        "੨"
      ],
      [
        "शुभम",
        "सुपर",
        "मार्केट"
      ]
    ]
  },
  "IMG_9729": {
    "annotations": [
      [
        "only",
        "for",
        "ladies"
      ],
      [
        "ப்பமே",
        "10am"
      ],
      [
        "19. റലം "
      ],
      [
        "अमेज",
        "पार्लर",
        "ਕਕਮਜਨਾਕਰਨਾਉ"
      ],
      [
        "maze"
      ],
      [
        "lets",
        "make",
        "over",
        "yourself"
      ],
      [
        "  "
      ],
      [
        "since",
        "2014"
      ]
    ]
  },
  "IMG_9733": {
    "annotations": [
      [
        "iphone"
      ],
      [
        "samsung"
      ],
      [
        "vivo",
        "obiletech"
      ],
      [
        "gadgets",
        "୦୦୦୦"
      ],
      [
        "google",
        "।्री",
        "गणेश"
      ],
      [
        "૧"
      ],
      [
        "oneplus",
        "मोबाईल",
        "ਟੇਕ",
        "ਮੱਛ",
        "गंजेदूस"
      ],
      [
        "motorola"
      ],
      [
        "੨",
        "realme",
        "hyperice",
        "ટ્ટ",
        "edifier"
      ],
      [
        "tecno"
      ]
    ]
  },
  "IMG_9740": {
    "annotations": [
      [
        "राम",
        "मेडिको"
      ],
      [
        "chemist",
        "",
        "druggist"
      ]
    ]
  },
  "IMG_9742": {
    "annotations": [
      [
        " "
      ],
      [
        "ડ",
        "visum",
        "ਸਾਰਾ"
      ],
      [
        "मोरया",
        "मोबाईल",
        "शॉपी"
      ],
      [
        "iphone",
        "vivo",
        "oppo"
      ]
    ]
  },
  "IMG_9743": {
    "annotations": [
      [
        "087",
        "no",
        "27fnups1016j1zg"
      ],
      [
        "किड्स",
        "बेअर"
      ],
      [
        "कैशन"
      ],
      [
        "mango",
        "tree",
        "collection"
      ]
    ]
  },
  "IMG_9812": {
    "annotations": [
      [
        "प्रस्‍थान",
        "प्रस्थान"
      ],
      [
        "ਤੇ",
        "parture"
      ]
    ]
  },
  "IMG_9815": {
    "annotations": [
      [
        "भारतीय",
        "विमानपत्तन",
        "प्राधिकरण"
      ],
      [
        "airports",
        "authority",
        "of",
        "india"
      ]
    ]
  },
  "IMG_9816": {
    "annotations": [
      [
        "वैद्यकीय",
        "कक्ष",
        "7",
        "चिकित्सा",
        "कक्ष"
      ],
      [
        "medical",
        "room"
      ]
    ]
  },
  "IMG_9818": {
    "annotations": [
      [
        "क्रॉसवर्ड",
        "ആഘോ"
      ],
      [
        "lamery",
        "crosswc"
      ],
      [
        "११०",
        "30",
        "ૠઙજઙઘઘછ",
        "1০ন",
        "jo",
        "non",
        "ਓਹ"
      ],
      [
        "hoo",
        "૧૮૦૭૭"
      ],
      [
        "ૠઙજઙઘઘછુતા",
        "ક"
      ],
      [
        "ஸுங்கங்"
      ],
      [
        "કનંદના"
      ],
      [
        "ਯਤੀ",
        "ਦਿਨਾਲ"
      ],
      [
        "धापत",
        "42012"
      ],
      [
        "रिफेव",
        "love",
        "hight",
        "maxi"
      ],
      [
        "ഝ"
      ],
      [
        "debsmitanrefe"
      ],
      [
        "અમ",
        "ਮੈਕਸ਼  "
      ],
      [
        "શંક",
        "થય"
      ]
    ]
  },
  "IMG_9820": {
    "annotations": [
      [
        "ದ್ರೈ   ",
        "സക്കസ്സ്",
        "ૠ",
        "ಶ್ರೀ",
        "വികസനം",
        "വികസനം",
        "എല്ലാവർക്കുമൊപ്പം",
        " ",
        "ਜੀ",
        "എല്ലാവർക്കും",
        "വികസനം",
        "starts"
      ],
      [
        "വികസനം",
        "ક"
      ],
      [
        "batteries"
      ],
      [
        "ਕੈਟਦੀ"
      ],
      [
        "ਕੱਟਦੀ"
      ]
    ]
  },
  "IMG_9821": {
    "annotations": [
      [
        " ",
        "ମାଠି"
      ],
      [
        "પરોલીસ"
      ],
      [
        "റഡു"
      ],
      [
        "power",
        "bank"
      ],
      [
        "पावर",
        "बैंक"
      ],
      [
        "पॉवर",
        "बैंक"
      ]
    ]
  },
  "IMG_9822": {
    "annotations": [
      [
        "୧୦ା"
      ],
      [
        "pow",
        "40000",
        "activ"
      ],
      [
        "41085",
        "power"
      ],
      [
        "50more",
        "૨૦૫૨૧"
      ],
      [
        "mosquito",
        "vaporiser"
      ],
      [
        "ਸਕਾਦ",
        "वेपोराइजर"
      ],
      [
        "डास",
        "वेपोरायज्ञार"
      ]
    ]
  },
  "IMG_9823": {
    "annotations": [
      [
        "dry",
        "coconut"
      ],
      [
        "सूखा",
        "नारियल"
      ],
      [
        "सुके",
        "नारक"
      ]
    ]
  },
  "IMG_9824": {
    "annotations": [
      [
        "odonil",
        "odonil",
        "odonil"
      ],
      [
        "room",
        "freshner"
      ],
      [
        "रूम",
        "फ्रेशनर"
      ],
      [
        "रूम",
        "फ्रेशनर"
      ]
    ]
  },
  "IMG_9825": {
    "annotations": [
      [
        "zippo"
      ],
      [
        "lighter"
      ],
      [
        "लाइटर"
      ],
      [
        "लाइटर"
      ]
    ]
  },
  "pic 10": {
    "annotations": [
      [
        "मिस्टर",
        "डी. आयायां."
      ],
      [
        "w",
        "5",
        "jiy"
      ]
    ]
  },
  "pic 2": {
    "annotations": [
      [
        "एलुरीसी तका"
      ],
      [
        "हाचनान्याद"
      ],
      [
        "blue",
        "berry",
        "cooperative"
      ],
      [
        "housing",
        "society",
        "limited"
      ]
    ]
  },
  "pic 9": {
    "annotations": [
      [
        "ਓ੝ਹਦ"
      ],
      [
        "pahadi",
        "bistro"
      ],
      [
        "दपहाडा",
        "শ্রী "
      ]
    ]
  }
}